<?xml version="1.0" encoding="UTF-8"?>
<krpano version="1.19"
        onstart="startup"
        logkey="false"
        bgcolor="#ffffff"
        projectfloorplanurl="%FIRSTXML%/floorplan/marietta_square_street_map.png"
        projecttitleid="project_title"
        projectdescriptionid="">


  <security cors="">
    <!--
    <crossdomainxml url="http://RESSOURCES_URL/crossdomain.xml" />
    -->
    <allowdomain domain="*" />
  </security>

  <krpano tour_firststartactiondone="false" />
  <events name="startbehavioursevents" onxmlcomplete="startbehavioursxmlcompleteaction();" keep="true"/>

  <!-- generated by Panotour Pro V2.5.13 64bits : 04-08-2018 13-45-08 -->
  <!-- Project file : S:/PROJECTS/VIRTUAL TOURS PROJECTS/VR TOURS COOKER/VRwithIntroTest/VRwithIntroTestProj.kpt -->
  <!-- Plugins and Spot Styles -->
  <include url="%FIRSTXML%/NORTHmariettaSquare_08032018_skin_vr.xml"/>
  <!-- Core actions -->
  <include url="%FIRSTXML%/NORTHmariettaSquare_08032018_core_vr.xml"/>
  <!-- Tour Messages -->
  <include url="%FIRSTXML%/NORTHmariettaSquare_08032018_messages_en.xml"/>

  <action name="startup">

    if (skipintro !== null, skipintroaction(); );

    if (s !== null, if (startscene === null OR startscene === "undefined", set(startscene, get(s));); );
    if (startscene === null OR startscene === "undefined",
      set(startscene, pano23);
    );
    if(startlanguage !== null AND startlanguage !== "undefined",
      set(tour_language, get(startlanguage));
    );
    if(starttime !== null AND starttime !== "undefined" AND starttime GT 0,
      set(videoscenestarttime, get(starttime));
    ,
      set(videoscenestarttime, 0);
    );
    if(scene[get(startscene)].full360,
    mainloadsceneStartup(get(startscene));
    if (h !== null,
      if (v !== null,
        if (f !== null,
          lookat(get(h), get(v), get(f));
         ,
          lookat(get(h), get(v));
        );
      ,
        if (f !== null,
          lookat(get(h), get(view.vlookat), get(f));
         ,
          lookat(get(h), get(view.vlookat));
        );
      );
    ,
      if (v !== null,
        if (f !== null,
          lookat(get(view.hlookat), get(v), get(f));
         ,
          lookat(get(view.hlookat), get(v));
        );
      ,
        if (f !== null,
          lookat(get(view.hlookat), get(view.vlookat), get(f));
        );
      );
    );
    );
  </action>

  <!-- 5 Groups -->

  <!-- Group Group 30 : 1 panoramas -->
  
<!-- **** @PanoName="CENTER N Art Mural" @PanoFile="S:/PROJECTS/VIRTUAL TOURS PROJECTS/VR TOURS COOKER/theShopsBetter/Pictures - The Square Shops/theShopsTouchedUp/CENTER N Art Mural.jpg" **** -->
<!-- **** Width="7776px" Height="3888px" **** -->
<scene name="pano23"
       heading="0"
       thumburl="%FIRSTXML%/center_n_art_mural_23/thumbnail.jpg"
       backgroundsound=""
       backgroundsoundloops="0"
       haspolygons="false"
       titleid="pano23_title"
       descriptionid=""
       multires="true"
       planar="false"
       full360="true"
       video="false"
       seen="false">
    <autorotate horizon="-4.545000" tofov="108.900000" waittime="1" speed="-3"/>
    <panoview h="-1.338750" v="-4.545000" fov="108.900000" hmin="-180" hmax="180" vmin="-90" vmax="90" fovmax="225" />
    <view fisheye="0"
          limitview="range"
          hlookatmin="-180"
          hlookatmax="180"
          vlookatmin="-90"
          vlookatmax="90"
          maxpixelzoom=""
          fovmin="9"
          fovtype="VFOV"
          fovmax="225"
          fov="108.900000"
          hlookat="-1.338750"
          vlookat="-4.545000"/>
    <preview url="%FIRSTXML%/center_n_art_mural_23/preview.jpg" type="CUBESTRIP" striporder="FRBLUD" />
    <image type="CUBE" multires="true" baseindex="0" tilesize="512" devices="!androidstock|webgl">
      <level tiledimagewidth="2560" tiledimageheight="2560">
          <front url="center_n_art_mural_23/0/2/%v_%u.jpg"/>
          <right url="center_n_art_mural_23/1/2/%v_%u.jpg"/>
          <back  url="center_n_art_mural_23/2/2/%v_%u.jpg"/>
          <left  url="center_n_art_mural_23/3/2/%v_%u.jpg"/>
          <up    url="center_n_art_mural_23/4/2/%v_%u.jpg"/>
          <down  url="center_n_art_mural_23/5/2/%v_%u.jpg"/>
      </level>
      <level tiledimagewidth="1536" tiledimageheight="1536">
          <front url="center_n_art_mural_23/0/1/%v_%u.jpg"/>
          <right url="center_n_art_mural_23/1/1/%v_%u.jpg"/>
          <back  url="center_n_art_mural_23/2/1/%v_%u.jpg"/>
          <left  url="center_n_art_mural_23/3/1/%v_%u.jpg"/>
          <up    url="center_n_art_mural_23/4/1/%v_%u.jpg"/>
          <down  url="center_n_art_mural_23/5/1/%v_%u.jpg"/>
      </level>
      <level tiledimagewidth="1024" tiledimageheight="1024">
          <front url="center_n_art_mural_23/0/0/%v_%u.jpg"/>
          <right url="center_n_art_mural_23/1/0/%v_%u.jpg"/>
          <back  url="center_n_art_mural_23/2/0/%v_%u.jpg"/>
          <left  url="center_n_art_mural_23/3/0/%v_%u.jpg"/>
          <up    url="center_n_art_mural_23/4/0/%v_%u.jpg"/>
          <down  url="center_n_art_mural_23/5/0/%v_%u.jpg"/>
      </level>
    </image>
    <image type="CUBE" devices="androidstock.and.no-webgl">
      <front url="center_n_art_mural_23/mobile/0.jpg"/>
      <right url="center_n_art_mural_23/mobile/1.jpg"/>
      <back  url="center_n_art_mural_23/mobile/2.jpg"/>
      <left  url="center_n_art_mural_23/mobile/3.jpg"/>
      <up    url="center_n_art_mural_23/mobile/4.jpg"/>
      <down  url="center_n_art_mural_23/mobile/5.jpg"/>
    </image>




  <!-- **** 3 Point Spots **** -->





  <hotspot name="spotpoint47"
           ath="-89.283957" atv="-0.478801"
           style="IconMoveHere1"
           tag="point"
           distorted="true"
           depth="1000"
           descriptionid=""
           linktarget="pano40"
           onclick="onclickspotpoint47"
           />
  <hotspot name="spotpoint47" devices="flash" zorder="3"/>
  <hotspot name="spotpoint47" devices="html5" zorder="3" zorder2="1"/>
  <action name="onclickspotpoint47">
  
        mainloadscene(pano40);


  </action>







  <hotspot name="spotpoint51"
           ath="97.400515" atv="1.436216"
           style="IconMoveHere1"
           tag="point"
           distorted="true"
           depth="1000"
           descriptionid=""
           linktarget="pano25"
           onclick="onclickspotpoint51"
           />
  <hotspot name="spotpoint51" devices="flash" zorder="3"/>
  <hotspot name="spotpoint51" devices="html5" zorder="3" zorder2="1"/>
  <action name="onclickspotpoint51">
  
        mainloadscene(pano25);


  </action>






  <action name="hidepanopointspots">



    set(hotspot[spotpoint47].visible, false);



    set(hotspot[spotpoint51].visible, false);



  </action>
  <action name="showpanopointspots">



  
  set(hotspot[spotpoint47].visible, true);



  
  set(hotspot[spotpoint51].visible, true);



  </action>
  <events name="pano23stopanimatedspots" onremovepano="" />


  <action name="showpanospotsaction">
    if (tour_displayspots,
    showpanopointspots();
    );
  </action>
  <action name="hidepanospotsaction">
    hidepanopointspots();
  </action>


</scene>

  <!-- Group Group 31 : 1 panoramas -->
  
<!-- **** @PanoName="CENTER N" @PanoFile="S:/PROJECTS/VIRTUAL TOURS PROJECTS/VR TOURS COOKER/theShopsBetter/Pictures - The Square Shops/theShopsTouchedUp/CENTER N.jpg" **** -->
<!-- **** Width="7776px" Height="3888px" **** -->
<scene name="pano24"
       heading="0"
       thumburl="%FIRSTXML%/center_n_24/thumbnail.jpg"
       backgroundsound=""
       backgroundsoundloops="0"
       haspolygons="false"
       titleid="pano24_title"
       descriptionid=""
       multires="true"
       planar="false"
       full360="true"
       video="false"
       seen="false">
    <autorotate horizon="-2.475000" tofov="90.000000" waittime="1" speed="-3"/>
    <panoview h="128.700000" v="-2.475000" fov="90.000000" hmin="-180" hmax="180" vmin="-90" vmax="90" fovmax="225" />
    <view fisheye="0"
          limitview="range"
          hlookatmin="-180"
          hlookatmax="180"
          vlookatmin="-90"
          vlookatmax="90"
          maxpixelzoom=""
          fovmin="9"
          fovtype="VFOV"
          fovmax="225"
          fov="90.000000"
          hlookat="128.700000"
          vlookat="-2.475000"/>
    <preview url="%FIRSTXML%/center_n_24/preview.jpg" type="CUBESTRIP" striporder="FRBLUD" />
    <image type="CUBE" multires="true" baseindex="0" tilesize="512" devices="!androidstock|webgl">
      <level tiledimagewidth="2560" tiledimageheight="2560">
          <front url="center_n_24/0/2/%v_%u.jpg"/>
          <right url="center_n_24/1/2/%v_%u.jpg"/>
          <back  url="center_n_24/2/2/%v_%u.jpg"/>
          <left  url="center_n_24/3/2/%v_%u.jpg"/>
          <up    url="center_n_24/4/2/%v_%u.jpg"/>
          <down  url="center_n_24/5/2/%v_%u.jpg"/>
      </level>
      <level tiledimagewidth="1536" tiledimageheight="1536">
          <front url="center_n_24/0/1/%v_%u.jpg"/>
          <right url="center_n_24/1/1/%v_%u.jpg"/>
          <back  url="center_n_24/2/1/%v_%u.jpg"/>
          <left  url="center_n_24/3/1/%v_%u.jpg"/>
          <up    url="center_n_24/4/1/%v_%u.jpg"/>
          <down  url="center_n_24/5/1/%v_%u.jpg"/>
      </level>
      <level tiledimagewidth="1024" tiledimageheight="1024">
          <front url="center_n_24/0/0/%v_%u.jpg"/>
          <right url="center_n_24/1/0/%v_%u.jpg"/>
          <back  url="center_n_24/2/0/%v_%u.jpg"/>
          <left  url="center_n_24/3/0/%v_%u.jpg"/>
          <up    url="center_n_24/4/0/%v_%u.jpg"/>
          <down  url="center_n_24/5/0/%v_%u.jpg"/>
      </level>
    </image>
    <image type="CUBE" devices="androidstock.and.no-webgl">
      <front url="center_n_24/mobile/0.jpg"/>
      <right url="center_n_24/mobile/1.jpg"/>
      <back  url="center_n_24/mobile/2.jpg"/>
      <left  url="center_n_24/mobile/3.jpg"/>
      <up    url="center_n_24/mobile/4.jpg"/>
      <down  url="center_n_24/mobile/5.jpg"/>
    </image>




  <!-- **** 2 Point Spots **** -->





  <hotspot name="spotpoint46"
           ath="0.477369" atv="-2.872260"
           style="IconMoveHere1"
           tag="point"
           distorted="true"
           depth="1000"
           descriptionid=""
           linktarget="pano25"
           onclick="onclickspotpoint46"
           />
  <hotspot name="spotpoint46" devices="flash" zorder="3"/>
  <hotspot name="spotpoint46" devices="html5" zorder="3" zorder2="1"/>
  <action name="onclickspotpoint46">
  
        mainloadscene(pano25);


  </action>







  <hotspot name="spotpoint52"
           ath="-172.360728" atv="-3.829862"
           style="IconMoveHere1"
           tag="point"
           distorted="true"
           depth="1000"
           descriptionid=""
           linktarget="pano39"
           onclick="onclickspotpoint52"
           />
  <hotspot name="spotpoint52" devices="flash" zorder="3"/>
  <hotspot name="spotpoint52" devices="html5" zorder="3" zorder2="1"/>
  <action name="onclickspotpoint52">
  
        mainloadscene(pano39);


  </action>



  <action name="hidepanopointspots">



    set(hotspot[spotpoint46].visible, false);



    set(hotspot[spotpoint52].visible, false);
  </action>
  <action name="showpanopointspots">



  
  set(hotspot[spotpoint46].visible, true);



  
  set(hotspot[spotpoint52].visible, true);
  </action>
  <events name="pano24stopanimatedspots" onremovepano="" />


  <action name="showpanospotsaction">
    if (tour_displayspots,
    showpanopointspots();
    );
  </action>
  <action name="hidepanospotsaction">
    hidepanopointspots();
  </action>


</scene>

  <!-- Group Group 32 : 1 panoramas -->
  
<!-- **** @PanoName="CENTER North" @PanoFile="S:/PROJECTS/VIRTUAL TOURS PROJECTS/VR TOURS COOKER/theShopsBetter/Pictures - The Square Shops/theShopsTouchedUp/CENTER North.jpg" **** -->
<!-- **** Width="7776px" Height="3888px" **** -->
<scene name="pano25"
       heading="0"
       thumburl="%FIRSTXML%/center_north_25/thumbnail.jpg"
       backgroundsound=""
       backgroundsoundloops="0"
       haspolygons="false"
       titleid="pano25_title"
       descriptionid=""
       multires="true"
       planar="false"
       full360="true"
       video="false"
       seen="false">
    <autorotate horizon="8.775000" tofov="90.000000" waittime="1" speed="-3"/>
    <panoview h="100.800000" v="8.775000" fov="90.000000" hmin="-180" hmax="180" vmin="-90" vmax="90" fovmax="225" />
    <view fisheye="0"
          limitview="range"
          hlookatmin="-180"
          hlookatmax="180"
          vlookatmin="-90"
          vlookatmax="90"
          maxpixelzoom=""
          fovmin="9"
          fovtype="VFOV"
          fovmax="225"
          fov="90.000000"
          hlookat="100.800000"
          vlookat="8.775000"/>
    <preview url="%FIRSTXML%/center_north_25/preview.jpg" type="CUBESTRIP" striporder="FRBLUD" />
    <image type="CUBE" multires="true" baseindex="0" tilesize="512" devices="!androidstock|webgl">
      <level tiledimagewidth="2560" tiledimageheight="2560">
          <front url="center_north_25/0/2/%v_%u.jpg"/>
          <right url="center_north_25/1/2/%v_%u.jpg"/>
          <back  url="center_north_25/2/2/%v_%u.jpg"/>
          <left  url="center_north_25/3/2/%v_%u.jpg"/>
          <up    url="center_north_25/4/2/%v_%u.jpg"/>
          <down  url="center_north_25/5/2/%v_%u.jpg"/>
      </level>
      <level tiledimagewidth="1536" tiledimageheight="1536">
          <front url="center_north_25/0/1/%v_%u.jpg"/>
          <right url="center_north_25/1/1/%v_%u.jpg"/>
          <back  url="center_north_25/2/1/%v_%u.jpg"/>
          <left  url="center_north_25/3/1/%v_%u.jpg"/>
          <up    url="center_north_25/4/1/%v_%u.jpg"/>
          <down  url="center_north_25/5/1/%v_%u.jpg"/>
      </level>
      <level tiledimagewidth="1024" tiledimageheight="1024">
          <front url="center_north_25/0/0/%v_%u.jpg"/>
          <right url="center_north_25/1/0/%v_%u.jpg"/>
          <back  url="center_north_25/2/0/%v_%u.jpg"/>
          <left  url="center_north_25/3/0/%v_%u.jpg"/>
          <up    url="center_north_25/4/0/%v_%u.jpg"/>
          <down  url="center_north_25/5/0/%v_%u.jpg"/>
      </level>
    </image>
    <image type="CUBE" devices="androidstock.and.no-webgl">
      <front url="center_north_25/mobile/0.jpg"/>
      <right url="center_north_25/mobile/1.jpg"/>
      <back  url="center_north_25/mobile/2.jpg"/>
      <left  url="center_north_25/mobile/3.jpg"/>
      <up    url="center_north_25/mobile/4.jpg"/>
      <down  url="center_north_25/mobile/5.jpg"/>
    </image>




  <!-- **** 2 Point Spots **** -->





  <hotspot name="spotpoint48"
           ath="12.150364" atv="5.755141"
           style="IconMoveHere1"
           tag="point"
           distorted="true"
           depth="1000"
           descriptionid=""
           linktarget="pano23"
           onclick="onclickspotpoint48"
           />
  <hotspot name="spotpoint48" devices="flash" zorder="3"/>
  <hotspot name="spotpoint48" devices="html5" zorder="3" zorder2="1"/>
  <action name="onclickspotpoint48">
  
        mainloadscene(pano23);


  </action>







  <hotspot name="spotpoint50"
           ath="175.703037" atv="-2.393641"
           style="IconMoveHere1"
           tag="point"
           distorted="true"
           depth="1000"
           descriptionid=""
           linktarget="pano24"
           onclick="onclickspotpoint50"
           />
  <hotspot name="spotpoint50" devices="flash" zorder="3"/>
  <hotspot name="spotpoint50" devices="html5" zorder="3" zorder2="1"/>
  <action name="onclickspotpoint50">
  
        mainloadscene(pano24);


  </action>



  <action name="hidepanopointspots">



    set(hotspot[spotpoint48].visible, false);



    set(hotspot[spotpoint50].visible, false);
  </action>
  <action name="showpanopointspots">



  
  set(hotspot[spotpoint48].visible, true);



  
  set(hotspot[spotpoint50].visible, true);
  </action>
  <events name="pano25stopanimatedspots" onremovepano="" />


  <action name="showpanospotsaction">
    if (tour_displayspots,
    showpanopointspots();
    );
  </action>
  <action name="hidepanospotsaction">
    hidepanopointspots();
  </action>


</scene>

  <!-- Group Group 41 : 1 panoramas -->
  
<!-- **** @PanoName="NE The Strand" @PanoFile="S:/PROJECTS/VIRTUAL TOURS PROJECTS/VR TOURS COOKER/theShopsBetter/Pictures - The Square Shops/theShopsTouchedUp/NE The Strand.jpg" **** -->
<!-- **** Width="7776px" Height="3888px" **** -->
<scene name="pano39"
       heading="0"
       thumburl="%FIRSTXML%/ne_the_strand_39/thumbnail.jpg"
       backgroundsound=""
       backgroundsoundloops="0"
       haspolygons="false"
       titleid="pano39_title"
       descriptionid=""
       multires="true"
       planar="false"
       full360="true"
       video="false"
       seen="false">
    <autorotate horizon="-8.325000" tofov="90.000000" waittime="1" speed="-3"/>
    <panoview h="50.850000" v="-8.325000" fov="90.000000" hmin="-180" hmax="180" vmin="-90" vmax="90" fovmax="225" />
    <view fisheye="0"
          limitview="range"
          hlookatmin="-180"
          hlookatmax="180"
          vlookatmin="-90"
          vlookatmax="90"
          maxpixelzoom=""
          fovmin="9"
          fovtype="VFOV"
          fovmax="225"
          fov="90.000000"
          hlookat="50.850000"
          vlookat="-8.325000"/>
    <preview url="%FIRSTXML%/ne_the_strand_39/preview.jpg" type="CUBESTRIP" striporder="FRBLUD" />
    <image type="CUBE" multires="true" baseindex="0" tilesize="512" devices="!androidstock|webgl">
      <level tiledimagewidth="2560" tiledimageheight="2560">
          <front url="ne_the_strand_39/0/2/%v_%u.jpg"/>
          <right url="ne_the_strand_39/1/2/%v_%u.jpg"/>
          <back  url="ne_the_strand_39/2/2/%v_%u.jpg"/>
          <left  url="ne_the_strand_39/3/2/%v_%u.jpg"/>
          <up    url="ne_the_strand_39/4/2/%v_%u.jpg"/>
          <down  url="ne_the_strand_39/5/2/%v_%u.jpg"/>
      </level>
      <level tiledimagewidth="1536" tiledimageheight="1536">
          <front url="ne_the_strand_39/0/1/%v_%u.jpg"/>
          <right url="ne_the_strand_39/1/1/%v_%u.jpg"/>
          <back  url="ne_the_strand_39/2/1/%v_%u.jpg"/>
          <left  url="ne_the_strand_39/3/1/%v_%u.jpg"/>
          <up    url="ne_the_strand_39/4/1/%v_%u.jpg"/>
          <down  url="ne_the_strand_39/5/1/%v_%u.jpg"/>
      </level>
      <level tiledimagewidth="1024" tiledimageheight="1024">
          <front url="ne_the_strand_39/0/0/%v_%u.jpg"/>
          <right url="ne_the_strand_39/1/0/%v_%u.jpg"/>
          <back  url="ne_the_strand_39/2/0/%v_%u.jpg"/>
          <left  url="ne_the_strand_39/3/0/%v_%u.jpg"/>
          <up    url="ne_the_strand_39/4/0/%v_%u.jpg"/>
          <down  url="ne_the_strand_39/5/0/%v_%u.jpg"/>
      </level>
    </image>
    <image type="CUBE" devices="androidstock.and.no-webgl">
      <front url="ne_the_strand_39/mobile/0.jpg"/>
      <right url="ne_the_strand_39/mobile/1.jpg"/>
      <back  url="ne_the_strand_39/mobile/2.jpg"/>
      <left  url="ne_the_strand_39/mobile/3.jpg"/>
      <up    url="ne_the_strand_39/mobile/4.jpg"/>
      <down  url="ne_the_strand_39/mobile/5.jpg"/>
    </image>




  <!-- **** 3 Point Spots **** -->





  <hotspot name="spotpoint43"
           ath="12.891233" atv="-4.787282"
           style="IconMoveHere1"
           tag="point"
           distorted="true"
           depth="1000"
           descriptionid=""
           linktarget="pano24"
           onclick="onclickspotpoint43"
           />
  <hotspot name="spotpoint43" devices="flash" zorder="3"/>
  <hotspot name="spotpoint43" devices="html5" zorder="3" zorder2="1"/>
  <action name="onclickspotpoint43">
  
        mainloadscene(pano24);


  </action>









  <action name="hidepanopointspots">



    set(hotspot[spotpoint43].visible, false);






  </action>
  <action name="showpanopointspots">



  
  set(hotspot[spotpoint43].visible, true);






  </action>
  <events name="pano39stopanimatedspots" onremovepano="" />


  <action name="showpanospotsaction">
    if (tour_displayspots,
    showpanopointspots();
    );
  </action>
  <action name="hidepanospotsaction">
    hidepanopointspots();
  </action>


</scene>

  <!-- Group Group 42 : 1 panoramas -->
  
<!-- **** @PanoName="NW CORNER" @PanoFile="S:/PROJECTS/VIRTUAL TOURS PROJECTS/VR TOURS COOKER/theShopsBetter/Pictures - The Square Shops/theShopsTouchedUp/NW CORNER.jpg" **** -->
<!-- **** Width="7776px" Height="3888px" **** -->
<scene name="pano40"
       heading="0"
       thumburl="%FIRSTXML%/nw_corner_40/thumbnail.jpg"
       backgroundsound=""
       backgroundsoundloops="0"
       haspolygons="false"
       titleid="pano40_title"
       descriptionid=""
       multires="true"
       planar="false"
       full360="true"
       video="false"
       seen="false">
    <autorotate horizon="4.956750" tofov="108.900000" waittime="1" speed="-3"/>
    <panoview h="-152.399000" v="4.956750" fov="108.900000" hmin="-180" hmax="180" vmin="-90" vmax="90" fovmax="225" />
    <view fisheye="0"
          limitview="range"
          hlookatmin="-180"
          hlookatmax="180"
          vlookatmin="-90"
          vlookatmax="90"
          maxpixelzoom=""
          fovmin="9"
          fovtype="VFOV"
          fovmax="225"
          fov="108.900000"
          hlookat="-152.399000"
          vlookat="4.956750"/>
    <preview url="%FIRSTXML%/nw_corner_40/preview.jpg" type="CUBESTRIP" striporder="FRBLUD" />
    <image type="CUBE" multires="true" baseindex="0" tilesize="512" devices="!androidstock|webgl">
      <level tiledimagewidth="2560" tiledimageheight="2560">
          <front url="nw_corner_40/0/2/%v_%u.jpg"/>
          <right url="nw_corner_40/1/2/%v_%u.jpg"/>
          <back  url="nw_corner_40/2/2/%v_%u.jpg"/>
          <left  url="nw_corner_40/3/2/%v_%u.jpg"/>
          <up    url="nw_corner_40/4/2/%v_%u.jpg"/>
          <down  url="nw_corner_40/5/2/%v_%u.jpg"/>
      </level>
      <level tiledimagewidth="1536" tiledimageheight="1536">
          <front url="nw_corner_40/0/1/%v_%u.jpg"/>
          <right url="nw_corner_40/1/1/%v_%u.jpg"/>
          <back  url="nw_corner_40/2/1/%v_%u.jpg"/>
          <left  url="nw_corner_40/3/1/%v_%u.jpg"/>
          <up    url="nw_corner_40/4/1/%v_%u.jpg"/>
          <down  url="nw_corner_40/5/1/%v_%u.jpg"/>
      </level>
      <level tiledimagewidth="1024" tiledimageheight="1024">
          <front url="nw_corner_40/0/0/%v_%u.jpg"/>
          <right url="nw_corner_40/1/0/%v_%u.jpg"/>
          <back  url="nw_corner_40/2/0/%v_%u.jpg"/>
          <left  url="nw_corner_40/3/0/%v_%u.jpg"/>
          <up    url="nw_corner_40/4/0/%v_%u.jpg"/>
          <down  url="nw_corner_40/5/0/%v_%u.jpg"/>
      </level>
    </image>
    <image type="CUBE" devices="androidstock.and.no-webgl">
      <front url="nw_corner_40/mobile/0.jpg"/>
      <right url="nw_corner_40/mobile/1.jpg"/>
      <back  url="nw_corner_40/mobile/2.jpg"/>
      <left  url="nw_corner_40/mobile/3.jpg"/>
      <up    url="nw_corner_40/mobile/4.jpg"/>
      <down  url="nw_corner_40/mobile/5.jpg"/>
    </image>




  <!-- **** 3 Point Spots **** -->





  <hotspot name="spotpoint49"
           ath="-121.923003" atv="0.068042"
           style="IconMoveHere1"
           tag="point"
           distorted="true"
           depth="1000"
           descriptionid=""
           linktarget="pano23"
           onclick="onclickspotpoint49"
           />
  <hotspot name="spotpoint49" devices="flash" zorder="3"/>
  <hotspot name="spotpoint49" devices="html5" zorder="3" zorder2="1"/>
  <action name="onclickspotpoint49">
  
        mainloadscene(pano23);


  </action>









  <action name="hidepanopointspots">



    set(hotspot[spotpoint49].visible, false);






  </action>
  <action name="showpanopointspots">



  
  set(hotspot[spotpoint49].visible, true);






  </action>
  <events name="pano40stopanimatedspots" onremovepano="" />


  <action name="showpanospotsaction">
    if (tour_displayspots,
    showpanopointspots();
    );
  </action>
  <action name="hidepanospotsaction">
    hidepanopointspots();
  </action>


</scene>

  <krpano nofullspherepanoavailable="false" />


  <!-- Awake HTML5 plugins -->
  <events name="eventKrpanoLoadedEvts" onxmlcomplete="eventKrpanoLoadedAction();" keep="true" />
  <action name="eventKrpanoLoadedAction">
    
    set(events[eventKrpanoLoadedEvts].name, null);
    js(eventKrpanoLoaded('webvr'));
  </action>

</krpano>

